telescopes/__init__.py
telescopes/_version.py
telescopes/handlers.py
telescopes/tests/__init__.py
telescopes/tests/test_handlers.py
telescopes-0.0.2.data/data/etc/jupyter/jupyter_notebook_config.d/telescopes.json
telescopes-0.0.2.data/data/etc/jupyter/jupyter_server_config.d/telescopes.json
telescopes-0.0.2.data/data/share/jupyter/labextensions/@datalayer/telescopes/build_log.json
telescopes-0.0.2.data/data/share/jupyter/labextensions/@datalayer/telescopes/package.json
telescopes-0.0.2.data/data/share/jupyter/labextensions/@datalayer/telescopes/schemas/@datalayer/telescopes/package.json.orig
telescopes-0.0.2.data/data/share/jupyter/labextensions/@datalayer/telescopes/schemas/@datalayer/telescopes/plugin.json
telescopes-0.0.2.data/data/share/jupyter/labextensions/@datalayer/telescopes/static/design_icons_lib_index_js.74a0a5c6e1aa2f225622.js
telescopes-0.0.2.data/data/share/jupyter/labextensions/@datalayer/telescopes/static/design_icons_lib_index_js.74a0a5c6e1aa2f225622.js.map
telescopes-0.0.2.data/data/share/jupyter/labextensions/@datalayer/telescopes/static/lib_index_js.2cce79825fbc6a1e7138.js
telescopes-0.0.2.data/data/share/jupyter/labextensions/@datalayer/telescopes/static/lib_index_js.2cce79825fbc6a1e7138.js.map
telescopes-0.0.2.data/data/share/jupyter/labextensions/@datalayer/telescopes/static/remoteEntry.0fc1afc7c8dbb935c987.js
telescopes-0.0.2.data/data/share/jupyter/labextensions/@datalayer/telescopes/static/remoteEntry.0fc1afc7c8dbb935c987.js.map
telescopes-0.0.2.data/data/share/jupyter/labextensions/@datalayer/telescopes/static/style.js
telescopes-0.0.2.data/data/share/jupyter/labextensions/@datalayer/telescopes/static/style_index_js.6adc4f09c76384370e06.js
telescopes-0.0.2.data/data/share/jupyter/labextensions/@datalayer/telescopes/static/style_index_js.6adc4f09c76384370e06.js.map
telescopes-0.0.2.dist-info/METADATA
telescopes-0.0.2.dist-info/WHEEL
telescopes-0.0.2.dist-info/licenses/LICENSE
telescopes-0.0.2.dist-info/RECORD
